LICENSE.txt
MANIFEST.in
README.rst
_sslkeylog.c
pyproject.toml
setup.cfg
setup.py
sslkeylog.py
openssl/1.0.2o/amd64/LICENSE
openssl/1.0.2o/amd64/include/openssl/aes.h
openssl/1.0.2o/amd64/include/openssl/asn1.h
openssl/1.0.2o/amd64/include/openssl/asn1_mac.h
openssl/1.0.2o/amd64/include/openssl/asn1t.h
openssl/1.0.2o/amd64/include/openssl/bio.h
openssl/1.0.2o/amd64/include/openssl/blowfish.h
openssl/1.0.2o/amd64/include/openssl/bn.h
openssl/1.0.2o/amd64/include/openssl/buffer.h
openssl/1.0.2o/amd64/include/openssl/camellia.h
openssl/1.0.2o/amd64/include/openssl/cast.h
openssl/1.0.2o/amd64/include/openssl/cmac.h
openssl/1.0.2o/amd64/include/openssl/cms.h
openssl/1.0.2o/amd64/include/openssl/comp.h
openssl/1.0.2o/amd64/include/openssl/conf.h
openssl/1.0.2o/amd64/include/openssl/conf_api.h
openssl/1.0.2o/amd64/include/openssl/crypto.h
openssl/1.0.2o/amd64/include/openssl/des.h
openssl/1.0.2o/amd64/include/openssl/des_old.h
openssl/1.0.2o/amd64/include/openssl/dh.h
openssl/1.0.2o/amd64/include/openssl/dsa.h
openssl/1.0.2o/amd64/include/openssl/dso.h
openssl/1.0.2o/amd64/include/openssl/dtls1.h
openssl/1.0.2o/amd64/include/openssl/e_os2.h
openssl/1.0.2o/amd64/include/openssl/ebcdic.h
openssl/1.0.2o/amd64/include/openssl/ec.h
openssl/1.0.2o/amd64/include/openssl/ecdh.h
openssl/1.0.2o/amd64/include/openssl/ecdsa.h
openssl/1.0.2o/amd64/include/openssl/engine.h
openssl/1.0.2o/amd64/include/openssl/err.h
openssl/1.0.2o/amd64/include/openssl/evp.h
openssl/1.0.2o/amd64/include/openssl/hmac.h
openssl/1.0.2o/amd64/include/openssl/krb5_asn.h
openssl/1.0.2o/amd64/include/openssl/kssl.h
openssl/1.0.2o/amd64/include/openssl/lhash.h
openssl/1.0.2o/amd64/include/openssl/md4.h
openssl/1.0.2o/amd64/include/openssl/md5.h
openssl/1.0.2o/amd64/include/openssl/modes.h
openssl/1.0.2o/amd64/include/openssl/obj_mac.h
openssl/1.0.2o/amd64/include/openssl/objects.h
openssl/1.0.2o/amd64/include/openssl/ocsp.h
openssl/1.0.2o/amd64/include/openssl/opensslconf.h
sslkeylog.egg-info/PKG-INFO
sslkeylog.egg-info/SOURCES.txt
sslkeylog.egg-info/dependency_links.txt
sslkeylog.egg-info/not-zip-safe
sslkeylog.egg-info/requires.txt
sslkeylog.egg-info/top_level.txt
