Metadata-Version: 2.4
Name: sslkeylog
Version: 0.5.2
Summary: Log SSL/TLS keys for decrypting SSL/TLS connections
Home-page: https://github.com/segevfiner/sslkeylog
Author: Segev Finer
Author-email: segev208@gmail.com
License: MIT
Project-URL: Documentation, https://sslkeylog.readthedocs.io/
Project-URL: Issue Tracker, https://github.com/segevfiner/sslkeylog/issues
Keywords: ssl tls sslkeylogfile
Classifier: Development Status :: 4 - Beta
Classifier: Intended Audience :: Developers
Classifier: Topic :: Security :: Cryptography
Classifier: Topic :: System :: Networking :: Monitoring
Classifier: License :: OSI Approved :: MIT License
Classifier: Programming Language :: Python :: 2
Classifier: Programming Language :: Python :: 2.7
Classifier: Programming Language :: Python :: 3
Classifier: Programming Language :: Python :: 3.5
Classifier: Programming Language :: Python :: 3.6
Classifier: Programming Language :: Python :: 3.7
Classifier: Programming Language :: Python :: 3.8
Classifier: Programming Language :: Python :: 3.9
Classifier: Programming Language :: Python :: 3.10
Classifier: Programming Language :: Python :: 3.11
Classifier: Programming Language :: Python :: 3.12
Classifier: Programming Language :: Python :: 3.13
License-File: LICENSE.txt
Provides-Extra: dev
Requires-Dist: flake8; extra == "dev"
Requires-Dist: pytest; extra == "dev"
Requires-Dist: pytest-metadata; extra == "dev"
Requires-Dist: mock; extra == "dev"
Requires-Dist: six; extra == "dev"
Requires-Dist: sphinx==5.*; python_version >= "3.0" and extra == "dev"
Dynamic: author
Dynamic: author-email
Dynamic: classifier
Dynamic: description
Dynamic: description-content-type
Dynamic: home-page
Dynamic: keywords
Dynamic: license
Dynamic: license-file
Dynamic: project-url
Dynamic: provides-extra
Dynamic: summary
